{"data": {"note": "sound_test/66218__percussionfiend__2.wav", "mode": "ABC notation", "half_steps_per_octave": "12", "trim": "1.0", "zero_note": "-10", "song": "X:1\nT:Honorable Miss Catherine Elliot\u2019s Reel\nM:C|\nL:1/8\nR:Reel\nB:John Pringle \u2013 A Collection of Reels, Strathspeys & Jigs (1801, p. 9)\nZ:AK/Fiddler\u2019s Companion\nK:A\ne|cABG A2 EA|FAdf ecBd|cABG A2 EA|dfEG A/A/A A:||\nd|ceag fgaf|gabg edce|ceag fgaf|gbaf e/e/e ec|\ndfag fedc|(dc)~BA BFFB|ceac dfbd|cABG A2 A||", "time_between_notes": "0.25", "invert_melody": false}}